osbot_github_actions/__init__.py
osbot_github_actions/utils/Version.py
osbot_github_actions/utils/__init__.py
osbot_github_actions/version
osbot_github_actions-0.13.1.dist-info/LICENSE
osbot_github_actions-0.13.1.dist-info/METADATA
osbot_github_actions-0.13.1.dist-info/WHEEL
osbot_github_actions-0.13.1.dist-info/RECORD
