Metadata-Version: 2.1
Name: osbot_github_actions
Version: 0.13.1
Summary: OWASP Security Bot - GitHub Actions
Home-page: https://github.com/owasp-sbot/OSBot-GitHub-Actions
License: MIT
Author: Dinis Cruz
Author-email: dinis.cruz@owasp.org
Requires-Python: >=3.7,<4.0
Classifier: License :: OSI Approved :: MIT License
Classifier: Programming Language :: Python :: 3
Classifier: Programming Language :: Python :: 3.7
Classifier: Programming Language :: Python :: 3.8
Classifier: Programming Language :: Python :: 3.9
Classifier: Programming Language :: Python :: 3.10
Classifier: Programming Language :: Python :: 3.11
Classifier: Programming Language :: Python :: 3.12
Requires-Dist: osbot_utils
Project-URL: Repository, https://github.com/owasp-sbot/OSBot-GitHub-Actions
